phonetisaurus/__init__.py
phonetisaurus/Phonetisaurus.so
phonetisaurus/commands.py
phonetisaurus/bin/interpolate-ngram
phonetisaurus/bin/phonetisaurus-g2prnn
phonetisaurus/bin/phonetisaurus-g2pfst
phonetisaurus/bin/phonetisaurus-arpa2wfst
phonetisaurus/bin/phonetisaurus-align
phonetisaurus/bin/estimate-ngram
phonetisaurus/bin/evaluate-ngram
phonetisaurus/bin/rnnlm
phonetisaurus_bindings.libs/libquadmath-d6be75ba.so.0.0.0
phonetisaurus_bindings.libs/libgfortran-1f0d579a.so.5.0.0
phonetisaurus_bindings-0.3.2.data/scripts/phonetisaurus-apply
phonetisaurus_bindings-0.3.2.data/scripts/phonetisaurus-train
phonetisaurus_bindings-0.3.2.dist-info/RECORD
phonetisaurus_bindings-0.3.2.dist-info/top_level.txt
phonetisaurus_bindings-0.3.2.dist-info/entry_points.txt
phonetisaurus_bindings-0.3.2.dist-info/METADATA
phonetisaurus_bindings-0.3.2.dist-info/WHEEL
