Metadata-Version: 2.1
Name: phonetisaurus-bindings
Version: 0.3.2
Summary: Phonetisaurus G2P python package (OpenFst-1.7.2)
Home-page: https://github.com/eginhard/phonetisaurus
Author: Josef Novak
Author-email: josef.robert.novak@gmail.com
Maintainer: Enno Hermann
Maintainer-email: enno.hermann@gmail.com
License: BSD
Project-URL: Repository, https://github.com/eginhard/phonetisaurus
Classifier: Programming Language :: Python
Classifier: Programming Language :: Python :: 3
Classifier: Programming Language :: Python :: 3.6
Classifier: Programming Language :: Python :: 3.7
Classifier: Programming Language :: Python :: 3.8
Classifier: Programming Language :: Python :: 3.9
Classifier: Programming Language :: Python :: 3.10
Classifier: Programming Language :: Python :: 3.11
Classifier: Programming Language :: Python :: 3.12
Classifier: Development Status :: 4 - Beta
Classifier: Intended Audience :: Science/Research
Classifier: Intended Audience :: Developers
Classifier: Operating System :: POSIX :: Linux
Classifier: License :: OSI Approved :: BSD License
Classifier: Topic :: Software Development
Classifier: Topic :: Software Development :: Libraries :: Python Modules
Classifier: Topic :: Multimedia :: Sound/Audio :: Speech
Classifier: Topic :: Multimedia :: Sound/Audio
Classifier: Topic :: Multimedia
Classifier: Topic :: Scientific/Engineering :: Artificial Intelligence
Requires-Python: >=3.6.0
Requires-Dist: bottle
